qmt/__init__.py
qmt/webapps/lib-qmt/lib-qmt.js
qmt/webapps/lib-qmt/favicon.png
qmt/webapps/lib-qmt/favicon.ico
qmt/webapps/lib-qmt/style.css
qmt/webapps/lib-qmt/assets/compass_rose.svg
qmt/webapps/lib-qmt/assets/compass_rose_north.svg
qmt/webapps/lib-qmt/assets/boxmodel.json
qmt/webapps/lib-qmt/assets/texture_imu.svg
qmt/webapps/view/imubox.html
qmt/webapps/view/boxmodel/package.json
qmt/webapps/view/boxmodel/vite.config.js
qmt/webapps/view/boxmodel/index.html
qmt/webapps/demo/imu-raw-data.html
qmt/webapps/demo/ui-gallery/package.json
qmt/webapps/demo/ui-gallery/vite.config.js
qmt/webapps/demo/ui-gallery/index.html
qmt/webapps/demo/template/package.json
qmt/webapps/demo/template/vite.config.js
qmt/webapps/demo/template/index.html
qmt/webapps/demo/full-body-tracking/package.json
qmt/webapps/demo/full-body-tracking/vite.config.js
qmt/webapps/demo/full-body-tracking/index.html
qmt/webapps/demo/orientation-estimation/package.json
qmt/webapps/demo/orientation-estimation/vite.config.js
qmt/webapps/demo/orientation-estimation/index.html
qmt/webapps/demo/euler-angles/package.json
qmt/webapps/demo/euler-angles/vite.config.js
qmt/webapps/demo/euler-angles/index.html
qmt/cpp/quaternion.cpp
qmt/cpp/quaternion.pyx
qmt/cpp/oriestimu.cpp
qmt/cpp/madgwick.pyx
qmt/cpp/madgwick.cpython-39-i386-linux-gnu.so
qmt/cpp/oriestimu.pyx
qmt/cpp/madgwick.cpp
qmt/cpp/oriestimu.cpython-39-i386-linux-gnu.so
qmt/cpp/__init__.py
qmt/cpp/quaternion.cpython-39-i386-linux-gnu.so
qmt/cpp/madgwick_src/MadgwickB.hpp
qmt/cpp/madgwick_src/MahonyAHRS.hpp
qmt/cpp/madgwick_src/MadgwickAHRS.cpp
qmt/cpp/madgwick_src/MahonyAHRS.cpp
qmt/cpp/madgwick_src/MadgwickB.cpp
qmt/cpp/madgwick_src/MadgwickAHRS.hpp
qmt/cpp/oriestimu_src/CsgOriEstIMU.hpp
qmt/cpp/oriestimu_src/CsgOriEstIMU.cpp
qmt/cpp/oriestimu_src/CSGutilities.cpp
qmt/cpp/oriestimu_src/CSGutilities.hpp
qmt/cpp/quaternion_src/quaternion.cpp
qmt/cpp/quaternion_src/quaternion.hpp
qmt/utils/webapp_aiohttp.py
qmt-0.2.4.dist-info/entry_points.txt
qmt-0.2.4.dist-info/RECORD
qmt-0.2.4.dist-info/top_level.txt
qmt-0.2.4.dist-info/METADATA
qmt-0.2.4.dist-info/WHEEL
