Metadata-Version: 2.1
Name: qmt
Version: 0.2.4
Summary: Quaternion-based Inertial Motion Tracking Toolbox
Home-page: https://github.com/dlaidig/qmt/
Author: Daniel Laidig
Author-email: laidig@control.tu-berlin.de
License: MIT
Project-URL: Documentation, https://qmt.readthedocs.io/
Classifier: Development Status :: 4 - Beta
Classifier: Intended Audience :: Science/Research
Classifier: License :: OSI Approved :: MIT License
Classifier: Programming Language :: Python :: 3
Requires-Python: >=3.8
Provides-Extra: dev
